{
  "version": "5.4.1",
  "flags": {},
  "shapes": [
    {
      "label": "simple bone cyst",
      "points": [
        [
          1466.5945945945946,
          936.036036036036
        ],
        [
          1576.5045045045044,
          1022.5225225225224
        ]
      ],
      "group_id": null,
      "description": "",
      "shape_type": "rectangle",
      "flags": {},
      "mask": null
    },
    {
      "label": "simple bone cyst",
      "points": [
        [
          1471.3939393939395,
          1004.2424242424241
        ],
        [
          1468.3636363636363,
          976.9696969696969
        ],
        [
          1468.3636363636363,
          953.3333333333333
        ],
        [
          1488.3636363636363,
          946.060606060606
        ],
        [
          1508.3636363636363,
          940.6060606060605
        ],
        [
          1536.8484848484848,
          941.8181818181818
        ],
        [
          1562.909090909091,
          948.4848484848484
        ],
        [
          1573.8181818181818,
          976.9696969696969
        ],
        [
          1570.1818181818182,
          995.1515151515151
        ],
        [
          1561.090909090909,
          1012.121212121212
        ],
        [
          1547.7575757575758,
          1020.6060606060605
        ],
        [
          1528.969696969697,
          1021.2121212121211
        ],
        [
          1490.7878787878788,
          1021.2121212121211
        ]
      ],
      "group_id": null,
      "description": "",
      "shape_type": "polygon",
      "flags": {},
      "mask": null
    }
  ],
  "imagePath": "IMG000582.jpeg",
  "imageData": null,
  "imageHeight": 3056,
  "imageWidth": 2544
}