{
  "version": "5.4.1",
  "flags": {},
  "shapes": [
    {
      "label": "osteochondroma",
      "points": [
        [
          826.7083333333334,
          1484.2708333333333
        ],
        [
          922.5416666666666,
          1576.9791666666667
        ]
      ],
      "group_id": null,
      "description": "",
      "shape_type": "rectangle",
      "flags": {},
      "mask": null
    },
    {
      "label": "osteochondroma",
      "points": [
        [
          833.421965317919,
          1570.4190751445087
        ],
        [
          829.3757225433525,
          1558.85838150289
        ],
        [
          828.2196531791907,
          1540.9393063583816
        ],
        [
          835.1560693641618,
          1532.2687861271677
        ],
        [
          851.9190751445086,
          1520.1300578034682
        ],
        [
          847.2947976878612,
          1504.5231213872833
        ],
        [
          847.2947976878612,
          1492.9624277456649
        ],
        [
          865.2138728323699,
          1492.3843930635837
        ],
        [
          880.2427745664739,
          1506.257225433526
        ],
        [
          906.2543352601156,
          1525.3323699421965
        ],
        [
          909.7225433526011,
          1531.6907514450868
        ],
        [
          920.1271676300578,
          1543.2514450867052
        ],
        [
          914.9248554913294,
          1556.5462427745665
        ],
        [
          895.8497109826588,
          1557.1242774566474
        ],
        [
          884.2890173410404,
          1557.1242774566474
        ],
        [
          877.9306358381502,
          1566.950867052023
        ],
        [
          861.1676300578034,
          1573.8872832369943
        ],
        [
          841.514450867052,
          1573.3092485549132
        ]
      ],
      "group_id": null,
      "description": "",
      "shape_type": "polygon",
      "flags": {},
      "mask": null
    }
  ],
  "imagePath": "IMG001218.jpeg",
  "imageData": null,
  "imageHeight": 2305,
  "imageWidth": 1768
}