{
  "version": "5.4.1",
  "flags": {},
  "shapes": [
    {
      "label": "synovial osteochondroma",
      "points": [
        [
          583.5506329113924,
          331.0632911392405
        ],
        [
          672.1582278481012,
          413.9746835443038
        ]
      ],
      "group_id": null,
      "description": "",
      "shape_type": "rectangle",
      "flags": {},
      "mask": null
    },
    {
      "label": "synovial osteochondroma",
      "points": [
        [
          587.4710144927536,
          390.7246376811594
        ],
        [
          584.2826086956521,
          377.1014492753623
        ],
        [
          586.6014492753623,
          366.66666666666663
        ],
        [
          604.5724637681159,
          355.07246376811594
        ],
        [
          618.4855072463768,
          333.9130434782609
        ],
        [
          634.7173913043478,
          333.9130434782609
        ],
        [
          648.3405797101449,
          345.2173913043478
        ],
        [
          656.4565217391304,
          352.17391304347825
        ],
        [
          664.8623188405796,
          369.27536231884056
        ],
        [
          667.7608695652174,
          383.18840579710144
        ],
        [
          667.7608695652174,
          398.2608695652174
        ],
        [
          663.4130434782608,
          405.7971014492753
        ],
        [
          655.0072463768115,
          410.7246376811594
        ],
        [
          638.7753623188405,
          411.30434782608694
        ],
        [
          617.3260869565216,
          409.27536231884056
        ],
        [
          597.0362318840579,
          402.3188405797101
        ],
        [
          590.0797101449275,
          399.1304347826087
        ]
      ],
      "group_id": null,
      "description": "",
      "shape_type": "polygon",
      "flags": {},
      "mask": null
    }
  ],
  "imagePath": "IMG001670.jpeg",
  "imageData": null,
  "imageHeight": 852,
  "imageWidth": 1019
}