{
  "version": "5.4.1",
  "flags": {},
  "shapes": [
    {
      "label": "other bt",
      "points": [
        [
          407.4349442379182,
          509.6654275092937
        ],
        [
          515.9851301115242,
          654.6468401486989
        ]
      ],
      "group_id": null,
      "description": "",
      "shape_type": "rectangle",
      "flags": {},
      "mask": null
    },
    {
      "label": "other bt",
      "points": [
        [
          434.98534798534797,
          647.2032967032967
        ],
        [
          420.69963369963364,
          633.6501831501832
        ],
        [
          411.9084249084249,
          619.7307692307693
        ],
        [
          410.0769230769231,
          595.9212454212454
        ],
        [
          408.6117216117216,
          575.0421245421246
        ],
        [
          410.4432234432235,
          542.8076923076924
        ],
        [
          416.6703296703297,
          527.7893772893773
        ],
        [
          444.1428571428571,
          517.8992673992674
        ],
        [
          461.72527472527474,
          512.0384615384615
        ],
        [
          495.79120879120876,
          512.0384615384615
        ],
        [
          504.9487179487179,
          522.6611721611722
        ],
        [
          508.97802197802196,
          539.8772893772895
        ],
        [
          514.4725274725274,
          561.489010989011
        ],
        [
          513.7399267399268,
          586.7637362637363
        ],
        [
          513.007326007326,
          602.8809523809524
        ],
        [
          505.3150183150183,
          619.7307692307693
        ],
        [
          497.2564102564103,
          631.8186813186813
        ],
        [
          490.2967032967033,
          642.441391941392
        ],
        [
          478.9413919413919,
          649.0347985347986
        ],
        [
          471.61538461538464,
          652.6978021978023
        ],
        [
          453.66666666666663,
          653.4304029304029
        ]
      ],
      "group_id": null,
      "description": "",
      "shape_type": "polygon",
      "flags": {},
      "mask": null
    }
  ],
  "imagePath": "IMG001785.jpeg",
  "imageData": null,
  "imageHeight": 801,
  "imageWidth": 574
}