{
  "version": "5.4.1",
  "flags": {},
  "shapes": [
    {
      "label": "osteochondroma",
      "points": [
        [
          1043.6226415094338,
          1363.2075471698113
        ],
        [
          1113.4339622641508,
          1502.830188679245
        ]
      ],
      "group_id": null,
      "description": "",
      "shape_type": "rectangle",
      "flags": {},
      "mask": null
    },
    {
      "label": "osteochondroma",
      "points": [
        [
          1098.2060085836908,
          1365.233905579399
        ],
        [
          1047.9914163090127,
          1432.1866952789699
        ],
        [
          1053.5708154506437,
          1432.1866952789699
        ],
        [
          1057.862660944206,
          1432.6158798283261
        ],
        [
          1060.008583690987,
          1438.195278969957
        ],
        [
          1061.2961373390558,
          1443.3454935622317
        ],
        [
          1063.0128755364806,
          1451.4999999999998
        ],
        [
          1063.0128755364806,
          1464.8047210300429
        ],
        [
          1063.0128755364806,
          1471.2424892703862
        ],
        [
          1064.7296137339056,
          1476.3927038626607
        ],
        [
          1068.1630901287554,
          1487.5515021459225
        ],
        [
          1072.0257510729614,
          1490.12660944206
        ],
        [
          1079.3218884120172,
          1497.4227467811158
        ],
        [
          1087.4763948497853,
          1497.4227467811158
        ],
        [
          1099.9227467811158,
          1479.8261802575105
        ],
        [
          1105.931330472103,
          1469.096566523605
        ],
        [
          1107.2188841201717,
          1445.920600858369
        ],
        [
          1108.0772532188842,
          1411.5858369098712
        ],
        [
          1108.5064377682402,
          1389.2682403433475
        ],
        [
          1108.0772532188842,
          1370.3841201716737
        ],
        [
          1102.9270386266094,
          1365.233905579399
        ]
      ],
      "group_id": null,
      "description": "",
      "shape_type": "polygon",
      "flags": {},
      "mask": null
    }
  ],
  "imagePath": "IMG001318.jpeg",
  "imageData": null,
  "imageHeight": 2303,
  "imageWidth": 1608
}