{
  "version": "5.4.1",
  "flags": {},
  "shapes": [
    {
      "label": "osteochondroma",
      "points": [
        [
          618.9784946236559,
          1307.4892473118282
        ],
        [
          683.494623655914,
          1424.693548387097
        ]
      ],
      "group_id": null,
      "description": "",
      "shape_type": "rectangle",
      "flags": {},
      "mask": null
    },
    {
      "label": "osteochondroma",
      "points": [
        [
          636.1256544502618,
          1321.9659685863874
        ],
        [
          648.6910994764397,
          1328.2486910994764
        ],
        [
          663.8743455497382,
          1337.6727748691098
        ],
        [
          669.109947643979,
          1353.3795811518326
        ],
        [
          661.7801047120419,
          1362.803664921466
        ],
        [
          657.068062827225,
          1369.086387434555
        ],
        [
          660.2094240837696,
          1387.4109947643979
        ],
        [
          666.4921465968586,
          1400.5
        ],
        [
          676.4397905759162,
          1418.8246073298428
        ],
        [
          669.6335078534031,
          1419.348167539267
        ],
        [
          659.1623036649214,
          1411.4947643979058
        ],
        [
          651.8324607329843,
          1401.5471204188482
        ],
        [
          646.5968586387434,
          1391.5994764397906
        ],
        [
          641.3612565445026,
          1384.2696335078533
        ],
        [
          630.3664921465968,
          1365.4214659685863
        ],
        [
          628.2722513089004,
          1351.2853403141362
        ],
        [
          624.6073298429319,
          1341.8612565445026
        ],
        [
          624.6073298429319,
          1327.7251308900525
        ],
        [
          627.7486910994764,
          1320.3952879581152
        ]
      ],
      "group_id": null,
      "description": "",
      "shape_type": "polygon",
      "flags": {},
      "mask": null
    }
  ],
  "imagePath": "IMG001063.jpeg",
  "imageData": null,
  "imageHeight": 2301,
  "imageWidth": 1610
}