{
  "version": "5.4.1",
  "flags": {},
  "shapes": [
    {
      "label": "osteochondroma",
      "points": [
        [
          706.056179775281,
          601.561797752809
        ],
        [
          852.5,
          888.75
        ]
      ],
      "group_id": null,
      "description": "",
      "shape_type": "rectangle",
      "flags": {},
      "mask": null
    },
    {
      "label": "osteochondroma",
      "points": [
        [
          826.25,
          610.0
        ],
        [
          784.375,
          625.625
        ],
        [
          739.375,
          653.125
        ],
        [
          721.25,
          703.75
        ],
        [
          716.875,
          758.75
        ],
        [
          716.875,
          805.625
        ],
        [
          726.25,
          853.75
        ],
        [
          729.375,
          880.625
        ],
        [
          740.0,
          885.625
        ],
        [
          748.125,
          874.375
        ],
        [
          780.625,
          841.875
        ],
        [
          788.75,
          825.625
        ],
        [
          796.25,
          833.75
        ],
        [
          816.25,
          852.5
        ],
        [
          830.0,
          857.5
        ],
        [
          836.25,
          846.25
        ],
        [
          841.875,
          827.5
        ],
        [
          845.0,
          787.5
        ],
        [
          849.375,
          713.75
        ],
        [
          847.5,
          691.875
        ],
        [
          835.625,
          636.875
        ],
        [
          830.0,
          617.5
        ]
      ],
      "group_id": null,
      "description": "",
      "shape_type": "polygon",
      "flags": {},
      "mask": null
    }
  ],
  "imagePath": "IMG001624.jpeg",
  "imageData": null,
  "imageHeight": 1502,
  "imageWidth": 1502
}