{
  "version": "5.4.1",
  "flags": {},
  "shapes": [
    {
      "label": "simple bone cyst",
      "points": [
        [
          244.1470588235294,
          719.7352941176471
        ],
        [
          412.38235294117646,
          1032.6764705882354
        ]
      ],
      "group_id": null,
      "description": "",
      "shape_type": "rectangle",
      "flags": {},
      "mask": null
    },
    {
      "label": "simple bone cyst",
      "points": [
        [
          339.066371681416,
          1023.8008849557522
        ],
        [
          316.94247787610624,
          991.5
        ],
        [
          289.5088495575222,
          957.8716814159292
        ],
        [
          270.0398230088496,
          917.6061946902655
        ],
        [
          251.45575221238943,
          874.6858407079646
        ],
        [
          245.7035398230089,
          835.3053097345132
        ],
        [
          250.12831858407088,
          807.429203539823
        ],
        [
          249.24336283185846,
          788.4026548672566
        ],
        [
          245.7035398230089,
          777.783185840708
        ],
        [
          249.68584070796464,
          744.5973451327434
        ],
        [
          261.63274336283195,
          734.4203539823009
        ],
        [
          276.6769911504425,
          723.358407079646
        ],
        [
          289.95132743362836,
          731.7654867256638
        ],
        [
          312.0752212389381,
          732.20796460177
        ],
        [
          339.95132743362836,
          723.358407079646
        ],
        [
          377.56194690265494,
          723.358407079646
        ],
        [
          397.91592920353986,
          749.9070796460177
        ],
        [
          403.6681415929204,
          772.4734513274336
        ],
        [
          403.6681415929204,
          817.6061946902655
        ],
        [
          407.20796460176996,
          867.6061946902655
        ],
        [
          407.65044247787614,
          909.1991150442478
        ],
        [
          402.78318584070803,
          941.9424778761062
        ],
        [
          397.0309734513275,
          959.641592920354
        ],
        [
          386.4115044247788,
          971.5884955752213
        ],
        [
          386.85398230088504,
          983.0929203539823
        ],
        [
          385.08407079646025,
          991.5
        ],
        [
          381.98672566371687,
          1001.2345132743362
        ],
        [
          381.5442477876107,
          1014.9513274336283
        ],
        [
          373.5796460176992,
          1022.0309734513274
        ],
        [
          366.50000000000006,
          1028.6681415929204
        ],
        [
          352.78318584070803,
          1028.6681415929204
        ]
      ],
      "group_id": null,
      "description": "",
      "shape_type": "polygon",
      "flags": {},
      "mask": null
    }
  ],
  "imagePath": "IMG001489.jpeg",
  "imageData": null,
  "imageHeight": 1583,
  "imageWidth": 933
}