{
  "version": "5.4.1",
  "flags": {},
  "shapes": [
    {
      "label": "osteosarcoma",
      "points": [
        [
          282.5,
          329.21428571428567
        ],
        [
          386.5,
          470.35714285714283
        ]
      ],
      "group_id": null,
      "description": "",
      "shape_type": "rectangle",
      "flags": {},
      "mask": null
    },
    {
      "label": "osteosarcoma",
      "points": [
        [
          322.69607843137254,
          467.6176470588235
        ],
        [
          315.44117647058823,
          466.6372549019608
        ],
        [
          303.87254901960785,
          450.16666666666663
        ],
        [
          293.48039215686276,
          432.3235294117647
        ],
        [
          286.0294117647059,
          424.0882352941176
        ],
        [
          283.87254901960785,
          412.51960784313724
        ],
        [
          283.48039215686276,
          391.5392156862745
        ],
        [
          286.8137254901961,
          370.3627450980392
        ],
        [
          308.38235294117646,
          353.30392156862746
        ],
        [
          318.7745098039216,
          344.28431372549016
        ],
        [
          322.30392156862746,
          334.0882352941176
        ],
        [
          335.44117647058823,
          330.95098039215685
        ],
        [
          347.79411764705884,
          330.95098039215685
        ],
        [
          355.2450980392157,
          335.0686274509804
        ],
        [
          361.51960784313724,
          343.30392156862746
        ],
        [
          365.6372549019608,
          357.8137254901961
        ],
        [
          371.71568627450984,
          372.9117647058823
        ],
        [
          383.6764705882353,
          387.61764705882354
        ],
        [
          384.65686274509807,
          396.6372549019608
        ],
        [
          384.8529411764706,
          410.55882352941177
        ],
        [
          380.53921568627453,
          418.7941176470588
        ],
        [
          381.51960784313724,
          431.5392156862745
        ],
        [
          359.7549019607843,
          418.59803921568624
        ],
        [
          360.1470588235294,
          432.7156862745098
        ],
        [
          359.1666666666667,
          437.8137254901961
        ],
        [
          358.1862745098039,
          447.02941176470586
        ],
        [
          358.38235294117646,
          451.5392156862745
        ],
        [
          358.38235294117646,
          455.656862745098
        ],
        [
          358.1862745098039,
          460.16666666666663
        ],
        [
          357.40196078431376,
          464.28431372549016
        ],
        [
          354.2647058823529,
          468.59803921568624
        ],
        [
          340.9313725490196,
          469.1862745098039
        ],
        [
          325.2450980392157,
          467.42156862745094
        ]
      ],
      "group_id": null,
      "description": "",
      "shape_type": "polygon",
      "flags": {},
      "mask": null
    }
  ],
  "imagePath": "IMG000201.jpeg",
  "imageData": null,
  "imageHeight": 767,
  "imageWidth": 605
}