{
  "version": "5.4.1",
  "flags": {},
  "shapes": [
    {
      "label": "osteochondroma",
      "points": [
        [
          55.88235294117649,
          766.4705882352941
        ],
        [
          329.4117647058823,
          1028.5294117647059
        ]
      ],
      "group_id": null,
      "description": "",
      "shape_type": "rectangle",
      "flags": {},
      "mask": null
    },
    {
      "label": "osteochondroma",
      "points": [
        [
          135.8823529411765,
          815.2941176470589
        ],
        [
          150.58823529411765,
          795.2941176470589
        ],
        [
          180.00000000000003,
          776.4705882352941
        ],
        [
          194.7058823529412,
          768.8235294117648
        ],
        [
          218.23529411764704,
          768.8235294117648
        ],
        [
          241.17647058823533,
          774.1176470588235
        ],
        [
          268.2352941176471,
          784.1176470588235
        ],
        [
          289.41176470588243,
          797.0588235294118
        ],
        [
          307.0588235294118,
          807.0588235294118
        ],
        [
          317.0588235294118,
          824.7058823529412
        ],
        [
          324.7058823529412,
          845.2941176470589
        ],
        [
          328.82352941176475,
          881.1764705882354
        ],
        [
          326.47058823529414,
          904.7058823529412
        ],
        [
          321.17647058823536,
          920.5882352941177
        ],
        [
          300.0,
          942.3529411764706
        ],
        [
          248.23529411764704,
          964.7058823529412
        ],
        [
          214.7058823529412,
          980.5882352941177
        ],
        [
          132.94117647058826,
          1018.8235294117648
        ],
        [
          103.52941176470588,
          1026.4705882352941
        ],
        [
          63.529411764705884,
          1018.2352941176471
        ],
        [
          59.41176470588235,
          990.5882352941177
        ],
        [
          70.00000000000003,
          955.2941176470589
        ]
      ],
      "group_id": null,
      "description": "",
      "shape_type": "polygon",
      "flags": {},
      "mask": null
    }
  ],
  "imagePath": "IMG000417.jpeg",
  "imageData": null,
  "imageHeight": 1570,
  "imageWidth": 800
}