{
  "version": "5.4.1",
  "flags": {},
  "shapes": [
    {
      "label": "osteochondroma",
      "points": [
        [
          468.54166666666663,
          1317.6458333333335
        ],
        [
          561.25,
          1378.0625
        ]
      ],
      "group_id": null,
      "description": "",
      "shape_type": "rectangle",
      "flags": {},
      "mask": null
    },
    {
      "label": "osteochondroma",
      "points": [
        [
          488.13609467455626,
          1323.6686390532545
        ],
        [
          560.9171597633136,
          1342.0118343195268
        ],
        [
          556.1834319526628,
          1359.7633136094676
        ],
        [
          555.0,
          1366.2721893491125
        ],
        [
          542.5739644970414,
          1369.2307692307693
        ],
        [
          522.4556213017752,
          1369.2307692307693
        ],
        [
          504.7041420118344,
          1369.2307692307693
        ],
        [
          489.319526627219,
          1365.680473372781
        ],
        [
          477.48520710059177,
          1357.9881656804735
        ],
        [
          473.9349112426036,
          1356.2130177514794
        ],
        [
          472.7514792899409,
          1346.1538461538462
        ],
        [
          478.6686390532545,
          1333.1360946745563
        ]
      ],
      "group_id": null,
      "description": "",
      "shape_type": "polygon",
      "flags": {},
      "mask": null
    }
  ],
  "imagePath": "IMG001294.jpeg",
  "imageData": null,
  "imageHeight": 2303,
  "imageWidth": 1610
}