{
  "version": "5.4.1",
  "flags": {},
  "shapes": [
    {
      "label": "other bt",
      "points": [
        [
          320.3824662813102,
          27.360308285163775
        ],
        [
          361.4229287090559,
          107.89980732177263
        ]
      ],
      "group_id": null,
      "description": "",
      "shape_type": "rectangle",
      "flags": {},
      "mask": null
    },
    {
      "label": "other bt",
      "points": [
        [
          424.8140655105973,
          162.23506743737957
        ],
        [
          451.01830443159923,
          223.12138728323697
        ]
      ],
      "group_id": null,
      "description": "",
      "shape_type": "rectangle",
      "flags": {},
      "mask": null
    },
    {
      "label": "other bt",
      "points": [
        [
          359.7014925373134,
          28.73134328358209
        ],
        [
          333.76865671641787,
          105.59701492537313
        ],
        [
          328.7313432835821,
          105.78358208955223
        ],
        [
          323.88059701492534,
          95.89552238805969
        ],
        [
          322.57462686567163,
          83.2089552238806
        ],
        [
          322.94776119402985,
          65.48507462686567
        ],
        [
          327.98507462686564,
          47.947761194029844
        ],
        [
          335.44776119402985,
          35.82089552238806
        ],
        [
          346.455223880597,
          30.03731343283582
        ]
      ],
      "group_id": null,
      "description": "",
      "shape_type": "polygon",
      "flags": {},
      "mask": null
    },
    {
      "label": "other bt",
      "points": [
        [
          442.5404624277457,
          164.93256262042388
        ],
        [
          426.7408477842004,
          221.1946050096339
        ],
        [
          433.8699421965318,
          218.49710982658956
        ],
        [
          438.4942196531792,
          210.98265895953756
        ],
        [
          443.3111753371869,
          198.26589595375722
        ],
        [
          446.77938342967246,
          185.54913294797686
        ],
        [
          448.89884393063585,
          173.41040462427745
        ],
        [
          448.89884393063585,
          165.70327552986512
        ],
        [
          445.23795761079,
          163.77649325626203
        ]
      ],
      "group_id": null,
      "description": "",
      "shape_type": "polygon",
      "flags": {},
      "mask": null
    }
  ],
  "imagePath": "IMG001753.jpeg",
  "imageData": null,
  "imageHeight": 1200,
  "imageWidth": 603
}