{
  "version": "5.4.1",
  "flags": {},
  "shapes": [
    {
      "label": "multiple osteochondromas",
      "points": [
        [
          277.32793522267207,
          27.103238866396822
        ],
        [
          318.2186234817814,
          227.50809716599196
        ]
      ],
      "group_id": null,
      "description": "",
      "shape_type": "rectangle",
      "flags": {},
      "mask": null
    },
    {
      "label": "multiple osteochondromas",
      "points": [
        [
          599.5951417004048,
          13.338056680162008
        ],
        [
          839.1523178807947,
          187.87086092715236
        ]
      ],
      "group_id": null,
      "description": "",
      "shape_type": "rectangle",
      "flags": {},
      "mask": null
    },
    {
      "label": "multiple osteochondromas",
      "points": [
        [
          273.6842105263158,
          416.17206477732793
        ],
        [
          388.663967611336,
          555.0384615384615
        ]
      ],
      "group_id": null,
      "description": "",
      "shape_type": "rectangle",
      "flags": {},
      "mask": null
    },
    {
      "label": "multiple osteochondromas",
      "points": [
        [
          575.7085020242914,
          359.4919028340081
        ],
        [
          627.1255060728745,
          499.97773279352225
        ]
      ],
      "group_id": null,
      "description": "",
      "shape_type": "rectangle",
      "flags": {},
      "mask": null
    },
    {
      "label": "multiple osteochondromas",
      "points": [
        [
          316.1943319838056,
          30.7469635627531
        ],
        [
          304.85829959514166,
          218.60121457489885
        ],
        [
          293.1174089068826,
          224.26923076923083
        ],
        [
          284.2105263157894,
          217.79149797570855
        ],
        [
          280.9716599190283,
          204.02631578947373
        ],
        [
          280.9716599190283,
          175.28137651821868
        ],
        [
          281.7813765182186,
          148.1558704453442
        ],
        [
          285.82995951417,
          141.6781376518219
        ],
        [
          293.92712550607285,
          132.7712550607288
        ],
        [
          298.3805668016194,
          122.24493927125512
        ],
        [
          298.3805668016194,
          99.57287449392719
        ],
        [
          298.3805668016194,
          90.26113360323893
        ],
        [
          301.21457489878543,
          74.06680161943326
        ],
        [
          305.668016194332,
          63.54048582995958
        ]
      ],
      "group_id": null,
      "description": "",
      "shape_type": "polygon",
      "flags": {},
      "mask": null
    },
    {
      "label": "multiple osteochondromas",
      "points": [
        [
          419.8380566801619,
          35.20040485829966
        ],
        [
          463.1578947368421,
          189.45141700404864
        ],
        [
          486.2348178137651,
          184.99797570850208
        ],
        [
          497.97570850202425,
          167.589068825911
        ],
        [
          504.85829959514166,
          131.55668016194338
        ],
        [
          504.85829959514166,
          100.38259109311747
        ],
        [
          507.2874493927125,
          74.06680161943326
        ],
        [
          500.4048582995951,
          51.79959514170047
        ],
        [
          482.1862348178137,
          41.67813765182193
        ],
        [
          472.87449392712546,
          35.20040485829966
        ],
        [
          465.99190283400804,
          25.078947368421115
        ],
        [
          456.6801619433198,
          23.86437246963569
        ],
        [
          448.582995951417,
          35.20040485829966
        ],
        [
          446.15384615384613,
          40.05870445344136
        ],
        [
          440.080971659919,
          39.65384615384622
        ]
      ],
      "group_id": null,
      "description": "",
      "shape_type": "polygon",
      "flags": {},
      "mask": null
    },
    {
      "label": "multiple osteochondromas",
      "points": [
        [
          286.2348178137652,
          540.0587044534414
        ],
        [
          280.5668016194332,
          509.6943319838057
        ],
        [
          276.11336032388664,
          478.11538461538464
        ],
        [
          285.42510121457485,
          457.8724696356275
        ],
        [
          294.331983805668,
          444.917004048583
        ],
        [
          312.5506072874494,
          432.7712550607288
        ],
        [
          338.0566801619433,
          419.41093117408906
        ],
        [
          351.41700404858295,
          425.07894736842104
        ],
        [
          370.4453441295546,
          455.03846153846155
        ],
        [
          374.0890688259109,
          482.5688259109312
        ],
        [
          384.2105263157894,
          519.006072874494
        ],
        [
          387.04453441295544,
          535.2004048582996
        ],
        [
          384.2105263157894,
          546.1315789473684
        ],
        [
          373.2793522267206,
          538.844129554656
        ],
        [
          366.80161943319837,
          531.9615384615386
        ],
        [
          359.5141700404858,
          531.5566801619434
        ],
        [
          351.41700404858295,
          538.4392712550608
        ],
        [
          343.7246963562753,
          545.7267206477733
        ],
        [
          332.79352226720647,
          552.6093117408907
        ],
        [
          310.52631578947364,
          551.7995951417005
        ],
        [
          297.165991902834,
          547.3461538461539
        ]
      ],
      "group_id": null,
      "description": "",
      "shape_type": "polygon",
      "flags": {},
      "mask": null
    },
    {
      "label": "multiple osteochondromas",
      "points": [
        [
          468.4210526315789,
          369.61336032388664
        ],
        [
          465.1821862348178,
          461.1113360323887
        ],
        [
          474.49392712550605,
          460.70647773279353
        ],
        [
          479.35222672064776,
          441.2732793522267
        ],
        [
          481.78137651821856,
          433.1761133603239
        ],
        [
          489.8785425101214,
          431.55668016194335
        ],
        [
          491.497975708502,
          441.2732793522267
        ],
        [
          489.4736842105263,
          450.585020242915
        ],
        [
          490.28340080971657,
          458.68218623481783
        ],
        [
          497.97570850202425,
          457.06275303643724
        ],
        [
          504.0485829959514,
          445.3218623481781
        ],
        [
          507.2874493927125,
          427.5080971659919
        ],
        [
          502.83400809716596,
          412.12348178137654
        ],
        [
          494.33198380566796,
          391.4757085020243
        ],
        [
          481.37651821862346,
          371.23279352226723
        ],
        [
          472.46963562753035,
          369.20850202429153
        ]
      ],
      "group_id": null,
      "description": "",
      "shape_type": "polygon",
      "flags": {},
      "mask": null
    },
    {
      "label": "multiple osteochondromas",
      "points": [
        [
          749.7975708502024,
          588.2368421052632
        ],
        [
          738.0566801619433,
          592.6902834008098
        ],
        [
          721.0526315789473,
          592.6902834008098
        ],
        [
          719.4331983805668,
          572.4473684210527
        ],
        [
          726.3157894736842,
          559.4919028340081
        ],
        [
          726.7206477732793,
          535.2004048582996
        ],
        [
          731.1740890688259,
          512.5283400809717
        ],
        [
          742.1052631578947,
          499.97773279352225
        ],
        [
          740.4858299595141,
          484.18825910931173
        ],
        [
          737.6518218623481,
          468.3987854251012
        ],
        [
          738.0566801619433,
          453.01417004048585
        ],
        [
          750.2024291497975,
          438.0344129554656
        ],
        [
          764.3724696356275,
          421.4352226720648
        ],
        [
          786.2348178137652,
          423.8643724696356
        ],
        [
          802.8340080971659,
          439.65384615384613
        ],
        [
          806.4777327935223,
          466.3744939271255
        ],
        [
          807.2874493927125,
          488.6417004048583
        ],
        [
          791.0931174089068,
          516.5769230769231
        ],
        [
          787.4493927125505,
          524.2692307692308
        ],
        [
          779.7570850202428,
          537.2246963562753
        ],
        [
          771.2550607287449,
          558.6821862348179
        ],
        [
          761.9433198380566,
          583.3785425101215
        ]
      ],
      "group_id": null,
      "description": "",
      "shape_type": "polygon",
      "flags": {},
      "mask": null
    },
    {
      "label": "multiple osteochondromas",
      "points": [
        [
          600.0,
          362.3259109311741
        ],
        [
          623.4817813765181,
          450.585020242915
        ],
        [
          613.7651821862348,
          455.03846153846155
        ],
        [
          610.1214574898785,
          451.7995951417004
        ],
        [
          604.0485829959514,
          455.8481781376518
        ],
        [
          602.0242914979757,
          461.92105263157896
        ],
        [
          602.0242914979757,
          471.23279352226723
        ],
        [
          600.8097165991902,
          484.99797570850205
        ],
        [
          592.7125506072874,
          495.1194331983806
        ],
        [
          585.4251012145749,
          495.92914979757086
        ],
        [
          577.7327935222671,
          475.2813765182186
        ],
        [
          577.7327935222671,
          470.0182186234818
        ],
        [
          582.995951417004,
          450.9898785425101
        ],
        [
          591.0931174089069,
          427.5080971659919
        ],
        [
          594.331983805668,
          409.2894736842105
        ],
        [
          595.1417004048583,
          389.04655870445345
        ],
        [
          595.5465587044534,
          389.04655870445345
        ]
      ],
      "group_id": null,
      "description": "",
      "shape_type": "polygon",
      "flags": {},
      "mask": null
    },
    {
      "label": "multiple osteochondromas",
      "points": [
        [
          598.3805668016194,
          174.87651821862354
        ],
        [
          607.2874493927125,
          125.8886639676114
        ],
        [
          616.5991902834007,
          70.42307692307699
        ],
        [
          623.8866396761133,
          28.317813765182247
        ],
        [
          629.5546558704453,
          24.26923076923083
        ],
        [
          637.6518218623481,
          44.51214574898792
        ],
        [
          638.8663967611335,
          61.51619433198387
        ],
        [
          647.3684210526316,
          63.54048582995958
        ],
        [
          649.7975708502024,
          50.1801619433199
        ],
        [
          661.9433198380566,
          33.58097165991909
        ],
        [
          678.9473684210526,
          31.15182186234824
        ],
        [
          687.4493927125505,
          42.89271255060735
        ],
        [
          697.5708502024291,
          32.36639676113367
        ],
        [
          705.6680161943319,
          24.674089068825975
        ],
        [
          717.0040485829959,
          16.57692307692314
        ],
        [
          729.1497975708502,
          15.76720647773286
        ],
        [
          743.7246963562752,
          29.532388663967673
        ],
        [
          748.5829959514169,
          40.868421052631646
        ],
        [
          755.0607287449392,
          51.79959514170047
        ],
        [
          762.3481781376518,
          61.92105263157901
        ],
        [
          776.9230769230769,
          71.6376518218624
        ],
        [
          789.8785425101214,
          76.49595141700411
        ],
        [
          804.0485829959514,
          87.02226720647779
        ],
        [
          819.8380566801619,
          84.1882591093118
        ],
        [
          832.3886639676113,
          82.16396761133609
        ],
        [
          836.0323886639676,
          93.50000000000006
        ],
        [
          835.6275303643724,
          103.21659919028346
        ],
        [
          827.9352226720647,
          110.504048582996
        ],
        [
          819.4331983805668,
          119.00607287449398
        ],
        [
          811.740890688259,
          133.58097165991907
        ],
        [
          807.2874493927125,
          146.53643724696363
        ],
        [
          804.0485829959514,
          153.82388663967618
        ],
        [
          802.4291497975707,
          163.54048582995958
        ],
        [
          797.5708502024291,
          182.56882591093122
        ]
      ],
      "group_id": null,
      "description": "",
      "shape_type": "polygon",
      "flags": {},
      "mask": null
    },
    {
      "label": "multiple osteochondromas",
      "points": [
        [
          417.40890688259105,
          21.43522267206484
        ],
        [
          509.7165991902834,
          192.69028340080976
        ]
      ],
      "group_id": null,
      "description": "",
      "shape_type": "rectangle",
      "flags": {},
      "mask": null
    },
    {
      "label": "multiple osteochondromas",
      "points": [
        [
          462.7530364372469,
          366.3744939271255
        ],
        [
          509.7165991902834,
          464.3502024291498
        ]
      ],
      "group_id": null,
      "description": "",
      "shape_type": "rectangle",
      "flags": {},
      "mask": null
    },
    {
      "label": "multiple osteochondromas",
      "points": [
        [
          716.5991902834007,
          419.00607287449395
        ],
        [
          810.5263157894736,
          597.5485829959515
        ]
      ],
      "group_id": null,
      "description": "",
      "shape_type": "rectangle",
      "flags": {},
      "mask": null
    }
  ],
  "imagePath": "IMG001686.jpeg",
  "imageData": null,
  "imageHeight": 887,
  "imageWidth": 1024
}