{
  "version": "5.4.1",
  "flags": {},
  "shapes": [
    {
      "label": "osteosarcoma",
      "points": [
        [
          121.71428571428572,
          17.0
        ],
        [
          371.42857142857144,
          329.57142857142856
        ]
      ],
      "group_id": null,
      "description": "",
      "shape_type": "rectangle",
      "flags": {},
      "mask": null
    },
    {
      "label": "osteosarcoma",
      "points": [
        [
          248.08290155440415,
          21.761658031088082
        ],
        [
          332.02072538860097,
          21.243523316062177
        ],
        [
          366.7357512953368,
          31.088082901554404
        ],
        [
          359.48186528497405,
          104.14507772020725
        ],
        [
          359.48186528497405,
          127.97927461139896
        ],
        [
          365.181347150259,
          180.82901554404145
        ],
        [
          365.181347150259,
          195.33678756476684
        ],
        [
          339.7927461139896,
          212.43523316062178
        ],
        [
          329.4300518134715,
          225.90673575129534
        ],
        [
          320.62176165803106,
          243.00518134715026
        ],
        [
          313.8860103626943,
          255.44041450777203
        ],
        [
          298.34196891191704,
          263.73056994818654
        ],
        [
          279.1709844559585,
          264.24870466321244
        ],
        [
          272.43523316062175,
          273.57512953367876
        ],
        [
          276.580310880829,
          295.33678756476684
        ],
        [
          270.88082901554395,
          313.9896373056995
        ],
        [
          227.8756476683937,
          317.0984455958549
        ],
        [
          175.54404145077717,
          317.0984455958549
        ],
        [
          137.72020725388597,
          302.07253886010363
        ],
        [
          127.35751295336786,
          266.32124352331607
        ],
        [
          137.20207253886008,
          235.23316062176167
        ],
        [
          152.74611398963725,
          192.7461139896373
        ],
        [
          162.07253886010358,
          151.29533678756476
        ],
        [
          162.07253886010358,
          130.5699481865285
        ],
        [
          159.99999999999994,
          87.56476683937824
        ],
        [
          176.58031088082896,
          58.54922279792746
        ],
        [
          200.41450777202067,
          40.41450777202073
        ],
        [
          241.86528497409319,
          21.761658031088082
        ]
      ],
      "group_id": null,
      "description": "",
      "shape_type": "polygon",
      "flags": {},
      "mask": null
    }
  ],
  "imagePath": "IMG001867.jpeg",
  "imageData": null,
  "imageHeight": 770,
  "imageWidth": 520
}