{
  "version": "5.4.1",
  "flags": {},
  "shapes": [
    {
      "label": "osteochondroma",
      "points": [
        [
          882.0512820512821,
          1265.8119658119658
        ],
        [
          958.974358974359,
          1451.2820512820513
        ]
      ],
      "group_id": null,
      "description": "",
      "shape_type": "rectangle",
      "flags": {},
      "mask": null
    },
    {
      "label": "osteochondroma",
      "points": [
        [
          890.1734104046243,
          1274.5664739884394
        ],
        [
          953.7572254335261,
          1425.4335260115606
        ],
        [
          951.4450867052024,
          1435.2601156069363
        ],
        [
          938.150289017341,
          1425.4335260115606
        ],
        [
          929.4797687861271,
          1417.3410404624278
        ],
        [
          925.4335260115607,
          1417.3410404624278
        ],
        [
          924.2774566473988,
          1427.7456647398844
        ],
        [
          925.4335260115607,
          1440.4624277456649
        ],
        [
          913.8728323699422,
          1442.7745664739884
        ],
        [
          901.1560693641619,
          1442.7745664739884
        ],
        [
          894.7976878612717,
          1432.3699421965318
        ],
        [
          893.0635838150289,
          1404.0462427745665
        ],
        [
          892.485549132948,
          1371.0982658959538
        ],
        [
          887.2832369942197,
          1287.8612716763007
        ]
      ],
      "group_id": null,
      "description": "",
      "shape_type": "polygon",
      "flags": {},
      "mask": null
    }
  ],
  "imagePath": "IMG000989.jpeg",
  "imageData": null,
  "imageHeight": 2302,
  "imageWidth": 2302
}