{
  "version": "5.4.1",
  "flags": {},
  "shapes": [
    {
      "label": "osteochondroma",
      "points": [
        [
          199.97328244274811,
          348.85496183206106
        ],
        [
          237.37786259541988,
          391.98473282442745
        ]
      ],
      "group_id": null,
      "description": "",
      "shape_type": "rectangle",
      "flags": {},
      "mask": null
    },
    {
      "label": "osteochondroma",
      "points": [
        [
          206.34920634920636,
          387.65432098765433
        ],
        [
          204.93827160493828,
          379.54144620811286
        ],
        [
          203.17460317460316,
          374.6031746031746
        ],
        [
          201.41093474426808,
          361.19929453262785
        ],
        [
          203.35097001763668,
          355.55555555555554
        ],
        [
          209.52380952380952,
          352.3809523809524
        ],
        [
          221.86948853615522,
          350.7936507936508
        ],
        [
          225.92592592592592,
          356.0846560846561
        ],
        [
          230.15873015873015,
          365.78483245149914
        ],
        [
          233.68606701940035,
          370.5467372134039
        ],
        [
          235.09700176366843,
          379.3650793650794
        ],
        [
          235.80246913580248,
          385.3615520282187
        ],
        [
          235.80246913580248,
          389.77072310405646
        ],
        [
          228.74779541446208,
          389.77072310405646
        ],
        [
          209.87654320987656,
          389.77072310405646
        ],
        [
          207.76014109347443,
          389.59435626102294
        ]
      ],
      "group_id": null,
      "description": "",
      "shape_type": "polygon",
      "flags": {},
      "mask": null
    }
  ],
  "imagePath": "IMG000826.jpeg",
  "imageData": null,
  "imageHeight": 757,
  "imageWidth": 703
}