{
  "version": "5.4.1",
  "flags": {},
  "shapes": [
    {
      "label": "osteochondroma",
      "points": [
        [
          383.7631578947368,
          1317.6447368421052
        ],
        [
          412.7105263157894,
          1384.75
        ]
      ],
      "group_id": null,
      "description": "",
      "shape_type": "rectangle",
      "flags": {},
      "mask": null
    },
    {
      "label": "osteochondroma",
      "points": [
        [
          392.30769230769226,
          1320.5955334987593
        ],
        [
          411.16625310173697,
          1348.8833746898263
        ],
        [
          408.1885856079404,
          1359.305210918114
        ],
        [
          399.0074441687345,
          1365.2605459057072
        ],
        [
          397.2704714640198,
          1370.471464019851
        ],
        [
          398.2630272952853,
          1379.9007444168733
        ],
        [
          398.2630272952853,
          1382.6302729528536
        ],
        [
          389.33002481389576,
          1380.6451612903224
        ],
        [
          385.85607940446647,
          1369.9751861042182
        ],
        [
          388.33746898263024,
          1359.305210918114
        ],
        [
          388.0893300248139,
          1347.394540942928
        ],
        [
          387.8411910669975,
          1335.483870967742
        ],
        [
          387.09677419354836,
          1326.0545905707195
        ],
        [
          387.3449131513647,
          1319.8511166253102
        ]
      ],
      "group_id": null,
      "description": "",
      "shape_type": "polygon",
      "flags": {},
      "mask": null
    }
  ],
  "imagePath": "IMG000567.jpeg",
  "imageData": null,
  "imageHeight": 2182,
  "imageWidth": 1382
}