{
  "version": "5.4.1",
  "flags": {},
  "shapes": [
    {
      "label": "other mt",
      "points": [
        [
          383.55172413793105,
          449.9655172413793
        ],
        [
          469.7586206896551,
          528.4137931034481
        ]
      ],
      "group_id": null,
      "description": "",
      "shape_type": "rectangle",
      "flags": {},
      "mask": null
    },
    {
      "label": "other mt",
      "points": [
        [
          393.1897106109325,
          510.90353697749197
        ],
        [
          389.33118971061094,
          489.68167202572346
        ],
        [
          387.7234726688103,
          467.8167202572347
        ],
        [
          391.2604501607717,
          460.7427652733119
        ],
        [
          403.8006430868167,
          458.17041800643085
        ],
        [
          415.3762057877814,
          458.491961414791
        ],
        [
          420.84244372990355,
          458.17041800643085
        ],
        [
          429.524115755627,
          455.91961414790995
        ],
        [
          445.60128617363347,
          454.3118971061093
        ],
        [
          460.07073954983923,
          453.9903536977492
        ],
        [
          462.9646302250804,
          469.1028938906752
        ],
        [
          465.5369774919614,
          486.7877813504823
        ],
        [
          466.18006430868166,
          504.1511254019292
        ],
        [
          463.2861736334405,
          514.7620578778134
        ],
        [
          439.491961414791,
          520.5498392282957
        ],
        [
          424.37942122186496,
          524.4083601286173
        ],
        [
          413.4469453376206,
          525.3729903536977
        ],
        [
          403.8006430868167,
          524.0868167202572
        ]
      ],
      "group_id": null,
      "description": "",
      "shape_type": "polygon",
      "flags": {},
      "mask": null
    }
  ],
  "imagePath": "IMG001748.jpeg",
  "imageData": null,
  "imageHeight": 1162,
  "imageWidth": 1024
}