{
  "version": "5.4.1",
  "flags": {},
  "shapes": [
    {
      "label": "multiple osteochondromas",
      "points": [
        [
          530.7521367521367,
          737.4444444444445
        ],
        [
          576.051282051282,
          930.6068376068376
        ]
      ],
      "group_id": null,
      "description": "",
      "shape_type": "rectangle",
      "flags": {},
      "mask": null
    },
    {
      "label": "multiple osteochondromas",
      "points": [
        [
          774.8510638297873,
          402.0425531914894
        ],
        [
          796.1276595744682,
          653.1063829787234
        ]
      ],
      "group_id": null,
      "description": "",
      "shape_type": "rectangle",
      "flags": {},
      "mask": null
    },
    {
      "label": "multiple osteochondromas",
      "points": [
        [
          778.5646437994724,
          430.07124010554094
        ],
        [
          779.3562005277046,
          649.8601583113457
        ],
        [
          783.5778364116096,
          650.1240105540898
        ],
        [
          787.7994722955146,
          644.3192612137204
        ],
        [
          790.4379947229552,
          570.1767810026386
        ],
        [
          792.8126649076518,
          521.3641160949869
        ],
        [
          792.8126649076518,
          496.2981530343008
        ],
        [
          790.7018469656992,
          465.69129287598946
        ],
        [
          790.7018469656992,
          446.6939313984169
        ],
        [
          785.160949868074,
          430.86279683377313
        ]
      ],
      "group_id": null,
      "description": "",
      "shape_type": "polygon",
      "flags": {},
      "mask": null
    },
    {
      "label": "multiple osteochondromas",
      "points": [
        [
          568.0105540897099,
          742.2084432717679
        ],
        [
          561.4142480211083,
          743.7915567282323
        ],
        [
          553.2348284960423,
          752.2348284960423
        ],
        [
          548.7493403693933,
          770.9683377308708
        ],
        [
          548.2216358839052,
          789.1741424802111
        ],
        [
          546.3746701846967,
          813.712401055409
        ],
        [
          545.8469656992086,
          829.2796833773087
        ],
        [
          544.2638522427442,
          846.693931398417
        ],
        [
          545.3192612137204,
          854.8733509234829
        ],
        [
          547.430079155673,
          859.358839050132
        ],
        [
          547.430079155673,
          864.6358839050133
        ],
        [
          540.0422163588391,
          871.759894459103
        ],
        [
          537.1398416886544,
          882.0501319261215
        ],
        [
          536.6121372031663,
          891.5488126649077
        ],
        [
          535.292875989446,
          902.6306068601584
        ],
        [
          536.8759894459104,
          918.4617414248022
        ],
        [
          541.6253298153035,
          914.2401055408972
        ],
        [
          545.5831134564645,
          895.2427440633246
        ],
        [
          546.3746701846967,
          899.7282321899737
        ],
        [
          553.7625329815304,
          884.6886543535621
        ],
        [
          574.3430079155673,
          801.3113456464381
        ],
        [
          568.0105540897099,
          800.78364116095
        ],
        [
          566.4274406332455,
          790.7572559366755
        ],
        [
          569.3298153034301,
          773.3430079155673
        ],
        [
          569.8575197889182,
          751.179419525066
        ]
      ],
      "group_id": null,
      "description": "",
      "shape_type": "polygon",
      "flags": {},
      "mask": null
    },
    {
      "label": "multiple osteochondromas",
      "points": [
        [
          813.3661971830987,
          845.774647887324
        ],
        [
          819.7042253521128,
          877.9342723004695
        ],
        [
          822.2863849765259,
          883.3333333333334
        ],
        [
          838.4835680751174,
          873.4741784037559
        ],
        [
          839.8920187793428,
          863.6150234741784
        ],
        [
          829.7981220657279,
          853.9906103286386
        ],
        [
          823.2253521126762,
          847.6525821596244
        ]
      ],
      "group_id": null,
      "description": "",
      "shape_type": "polygon",
      "flags": {},
      "mask": null
    },
    {
      "label": "multiple osteochondromas",
      "points": [
        [
          811.0187793427231,
          842.0187793427231
        ],
        [
          842.474178403756,
          886.1502347417841
        ]
      ],
      "group_id": null,
      "description": "",
      "shape_type": "rectangle",
      "flags": {},
      "mask": null
    }
  ],
  "imagePath": "IMG000300.jpeg",
  "imageData": null,
  "imageHeight": 1886,
  "imageWidth": 1388
}