{
  "version": "5.4.1",
  "flags": {},
  "shapes": [
    {
      "label": "other bt",
      "points": [
        [
          402.75257731958766,
          962.8865979381444
        ],
        [
          452.5730337078651,
          1326.4044943820224
        ]
      ],
      "group_id": null,
      "description": "",
      "shape_type": "rectangle",
      "flags": {},
      "mask": null
    },
    {
      "label": "other bt",
      "points": [
        [
          404.8144329896908,
          968.5567010309279
        ],
        [
          414.09278350515467,
          1308.7628865979382
        ],
        [
          428.52577319587635,
          1318.5567010309278
        ],
        [
          432.13402061855675,
          1280.4123711340208
        ],
        [
          445.5360824742269,
          1226.2886597938145
        ],
        [
          446.0515463917526,
          1171.1340206185566
        ],
        [
          449.14432989690727,
          1119.5876288659795
        ],
        [
          440.8969072164949,
          1045.360824742268
        ],
        [
          432.13402061855675,
          981.4432989690722
        ],
        [
          426.46391752577324,
          970.6185567010309
        ]
      ],
      "group_id": null,
      "description": "",
      "shape_type": "polygon",
      "flags": {},
      "mask": null
    }
  ],
  "imagePath": "IMG001724.jpeg",
  "imageData": null,
  "imageHeight": 1500,
  "imageWidth": 822
}