{
  "version": "5.4.1",
  "flags": {},
  "shapes": [
    {
      "label": "multiple osteochondromas",
      "points": [
        [
          804.0,
          539.4310344827586
        ],
        [
          974.689655172414,
          1039.4310344827586
        ]
      ],
      "group_id": null,
      "description": "",
      "shape_type": "rectangle",
      "flags": {},
      "mask": null
    },
    {
      "label": "multiple osteochondromas",
      "points": [
        [
          310.8965517241379,
          1299.7758620689656
        ],
        [
          829.8620689655172,
          1748.0517241379312
        ]
      ],
      "group_id": null,
      "description": "",
      "shape_type": "rectangle",
      "flags": {},
      "mask": null
    },
    {
      "label": "multiple osteochondromas",
      "points": [
        [
          961.8125000000001,
          689.0
        ],
        [
          949.3125000000001,
          596.8125
        ],
        [
          935.2500000000001,
          549.9375
        ],
        [
          889.9375000000001,
          554.625
        ],
        [
          871.1875000000001,
          612.4375
        ],
        [
          861.8125000000001,
          631.1875
        ],
        [
          836.8125000000001,
          696.8125
        ],
        [
          819.6250000000001,
          768.6875
        ],
        [
          819.6250000000001,
          828.0625
        ],
        [
          819.6250000000001,
          895.25
        ],
        [
          833.6875000000001,
          996.8125
        ],
        [
          843.0625000000001,
          1026.5
        ],
        [
          927.4375000000001,
          1015.5625
        ],
        [
          964.9375000000001,
          999.9375
        ]
      ],
      "group_id": null,
      "description": "",
      "shape_type": "polygon",
      "flags": {},
      "mask": null
    },
    {
      "label": "multiple osteochondromas",
      "points": [
        [
          318.3098591549296,
          1706.3380281690143
        ],
        [
          326.7605633802817,
          1643.661971830986
        ],
        [
          334.50704225352115,
          1619.718309859155
        ],
        [
          344.3661971830986,
          1590.8450704225354
        ],
        [
          423.94366197183103,
          1514.7887323943662
        ],
        [
          456.3380281690141,
          1492.2535211267607
        ],
        [
          527.4647887323944,
          1438.7323943661972
        ],
        [
          539.4366197183099,
          1390.1408450704225
        ],
        [
          558.4507042253522,
          1350.0
        ],
        [
          584.5070422535211,
          1330.9859154929577
        ],
        [
          650.0,
          1314.7887323943662
        ],
        [
          713.3802816901409,
          1320.4225352112676
        ],
        [
          750.7042253521128,
          1350.0
        ],
        [
          800.7042253521128,
          1342.2535211267607
        ],
        [
          828.1690140845071,
          1373.2394366197184
        ],
        [
          820.4225352112677,
          1483.0985915492959
        ],
        [
          790.1408450704225,
          1461.9718309859156
        ],
        [
          761.9718309859155,
          1461.9718309859156
        ],
        [
          732.3943661971831,
          1493.661971830986
        ],
        [
          709.1549295774648,
          1519.0140845070423
        ],
        [
          697.887323943662,
          1536.6197183098593
        ],
        [
          686.6197183098592,
          1566.9014084507044
        ],
        [
          647.887323943662,
          1606.3380281690143
        ],
        [
          603.5211267605634,
          1650.0
        ],
        [
          556.3380281690141,
          1692.9577464788733
        ],
        [
          511.2676056338028,
          1730.281690140845
        ],
        [
          485.21126760563385,
          1733.0985915492959
        ],
        [
          473.94366197183103,
          1718.3098591549297
        ],
        [
          476.056338028169,
          1675.3521126760563
        ],
        [
          471.830985915493,
          1640.8450704225354
        ],
        [
          466.19718309859155,
          1637.323943661972
        ],
        [
          430.2816901408451,
          1651.4084507042255
        ],
        [
          380.98591549295776,
          1671.830985915493
        ]
      ],
      "group_id": null,
      "description": "",
      "shape_type": "polygon",
      "flags": {},
      "mask": null
    }
  ],
  "imagePath": "IMG000995.jpeg",
  "imageData": null,
  "imageHeight": 2303,
  "imageWidth": 1608
}